AbemaStream/__init__.py
AbemaStream/__main__.py
AbemaStream/abemastream.py
AbemaStream-0.0.2.dist-info/LICENSE
AbemaStream-0.0.2.dist-info/METADATA
AbemaStream-0.0.2.dist-info/WHEEL
AbemaStream-0.0.2.dist-info/top_level.txt
AbemaStream-0.0.2.dist-info/RECORD
